detoxio/__init__.py
detoxio/adapters/__init__.py
detoxio/adapters/exceptions.py
detoxio/adapters/grpc.py
detoxio/adapters/prompts.py
detoxio/config.py
detoxio/filter.py
detoxio/models.py
detoxio/reporting.py
detoxio/scanner.py
detoxio/utils.py
detoxio-0.2.1.dist-info/METADATA
detoxio-0.2.1.dist-info/WHEEL
detoxio-0.2.1.dist-info/RECORD
